simplecalc/__init__.py
simplecalc/core.py
simplecalctest-0.1.0.dist-info/licenses/LICENSE
simplecalctest-0.1.0.dist-info/METADATA
simplecalctest-0.1.0.dist-info/WHEEL
simplecalctest-0.1.0.dist-info/top_level.txt
simplecalctest-0.1.0.dist-info/RECORD
