Metadata-Version: 2.4
Name: simplecalctest
Version: 0.1.0
Summary: A simple calculator library for addition and subtraction
Author-email: Mvenyi Donald <mvenyidonny1987@gmail.com>
License: MIT License
Requires-Python: >=3.7
License-File: LICENSE
Dynamic: license-file
